biocpy/__init__.py
biocpy/genomicranges/__init__.py
biocpy/multiassayexperiment/__init__.py
biocpy/singlecellexperiment/__init__.py
biocpy/summarizedexperiment/__init__.py
BiocPy-0.2.2.dist-info/LICENSE.txt
BiocPy-0.2.2.dist-info/METADATA
BiocPy-0.2.2.dist-info/WHEEL
BiocPy-0.2.2.dist-info/top_level.txt
BiocPy-0.2.2.dist-info/RECORD
