Metadata-Version: 2.1
Name: BiocPy
Version: 0.2.2
Summary: Interface to all [BiocPy](https://github.com/BiocPy) packages
Home-page: https://github.com/BiocPy/BiocPy
Author: jkanche
Author-email: jayaram.kancherla@gmail.com
License: MIT
Project-URL: Documentation, https://github.com/BiocPy/BiocPy
Platform: any
Classifier: Development Status :: 4 - Beta
Classifier: Programming Language :: Python
License-File: LICENSE.txt
Requires-Dist: biocframe
Requires-Dist: genomicranges
Requires-Dist: summarizedexperiment
Requires-Dist: singlecellexperiment
Requires-Dist: multiassayexperiment
Requires-Dist: rds2py
Requires-Dist: mopsy
Requires-Dist: pybiocfilecache
Requires-Dist: numpy
Requires-Dist: scipy
Requires-Dist: pandas
Requires-Dist: importlib-metadata ; python_version < "3.8"
Provides-Extra: testing
Requires-Dist: setuptools ; extra == 'testing'
Requires-Dist: pytest ; extra == 'testing'
Requires-Dist: pytest-cov ; extra == 'testing'
